acmsg/__init__.py
acmsg/__main__.py
acmsg/constants.py
acmsg/exceptions.py
acmsg/api/__init__.py
acmsg/api/openrouter.py
acmsg/cli/__init__.py
acmsg/cli/commands.py
acmsg/cli/parsers.py
acmsg/core/__init__.py
acmsg/core/config.py
acmsg/core/generation.py
acmsg/core/git.py
acmsg/templates/__init__.py
acmsg/templates/renderer.py
acmsg/templates/assets/__init__.py
acmsg/templates/assets/system_prompt.md
acmsg/templates/assets/template_config.yaml
acmsg/templates/assets/user_prompt.md
acmsg-0.3.1.dist-info/licenses/LICENSE
acmsg-0.3.1.dist-info/METADATA
acmsg-0.3.1.dist-info/WHEEL
acmsg-0.3.1.dist-info/entry_points.txt
acmsg-0.3.1.dist-info/top_level.txt
acmsg-0.3.1.dist-info/RECORD
