Metadata-Version: 2.4
Name: acmsg
Version: 0.3.1
Summary: Automatic git commit message generator using AI models & the OpenRouter API.
Author: Quinn Edenfield
Author-email: quinn@qeden.dev
Maintainer: Quinn Edenfield
Maintainer-email: quinn@qeden.dev
Project-URL: repository, https://github.com/quinneden/acmsg
Keywords: AI,OpenRouter,artificial intelligence,commit,commit message,git
Requires-Python: >=3.12
License-File: LICENSE
Requires-Dist: colorama<0.5.0,>=0.4.6
Requires-Dist: jinja2>=3.1.6
Requires-Dist: pyyaml<7.0.0,>=6.0.2
Requires-Dist: requests<3.0.0,>=2.32.3
Requires-Dist: types-colorama>=0.4.15.20240311
Requires-Dist: types-pyyaml>=6.0.12.20250402
Requires-Dist: types-requests>=2.32.0.20250328
Dynamic: license-file
